dagtool/__about__.py
dagtool/__init__.py
dagtool/__main__.py
dagtool/conf.py
dagtool/const.py
dagtool/factory.py
dagtool/loader.py
dagtool/renderer.py
dagtool/utils.py
dagtool/models/build_context.py
dagtool/models/dag.py
dagtool/models/datahub.py
dagtool/models/default_args.py
dagtool/models/sync.py
dagtool/models/task.py
dagtool/models/task_group.py
dagtool/models/tool.py
dagtool/models/variable.py
dagtool/providers/__init__.py
dagtool/providers/common/__init__.py
dagtool/providers/common/operators/__init__.py
dagtool/providers/common/operators/debug.py
dagtool/providers/common/operators/error.py
dagtool/tasks/__init__.py
dagtool/tasks/common/__init__.py
dagtool/tasks/common/custom_tool.py
dagtool/tasks/common/debug.py
dagtool/tasks/common/operator.py
dagtool/tasks/standard/__init__.py
dagtool/tasks/standard/bash.py
dagtool/tasks/standard/empty.py
dagtool/tasks/standard/python.py
dagtool-0.0.13.dist-info/METADATA
dagtool-0.0.13.dist-info/WHEEL
dagtool-0.0.13.dist-info/entry_points.txt
dagtool-0.0.13.dist-info/licenses/LICENSE
dagtool-0.0.13.dist-info/RECORD
