Metadata-Version: 2.4
Name: dagtool
Version: 0.0.13
Summary: a friendly airflow dag build tool
Project-URL: Homepage, https://github.com/ddeutils/dagtool/
Project-URL: Source Code, https://github.com/ddeutils/dagtool/
License-File: LICENSE
Classifier: Development Status :: 4 - Beta
Classifier: License :: OSI Approved :: MIT License
Classifier: Natural Language :: English
Classifier: Operating System :: OS Independent
Classifier: Programming Language :: Python
Classifier: Programming Language :: Python :: 3 :: Only
Classifier: Programming Language :: Python :: 3.10
Classifier: Programming Language :: Python :: 3.11
Classifier: Programming Language :: Python :: 3.12
Classifier: Programming Language :: Python :: 3.13
Classifier: Topic :: Utilities
Requires-Python: >=3.10
Requires-Dist: apache-airflow>=2.7.1
Requires-Dist: pydantic>=2.9.2
Provides-Extra: dev
Requires-Dist: clishelf>=0.2.22; extra == 'dev'
Requires-Dist: coverage>=7.10.0; extra == 'dev'
Requires-Dist: pre-commit>=4.0.0; extra == 'dev'
Requires-Dist: pytest>=8.4.0; extra == 'dev'
